LICENSE
MANIFEST.in
README.md
setup.py
tests.py
ReliefF/ReliefF.py
ReliefF/__init__.py
ReliefF/_version.py
ReliefF.egg-info/PKG-INFO
ReliefF.egg-info/SOURCES.txt
ReliefF.egg-info/dependency_links.txt
ReliefF.egg-info/requires.txt
ReliefF.egg-info/top_level.txt
ReliefF.egg-info/zip-safe