Metadata-Version: 1.1
Name: ReliefF
Version: 0.1.1
Summary: ReliefF feature selection algorithms
Home-page: https://github.com/rhiever/ReliefF
Author: Randal S. Olson
Author-email: rso@randalolson.com
License: License :: OSI Approved :: MIT License
Keywords: feature selection,feature preprocessing,machine learning,data science,supervised classification,feature importance,epistasis,genetic analysis
Platform: UNKNOWN
Classifier: Intended Audience :: Developers
Classifier: Intended Audience :: Information Technology
Classifier: Intended Audience :: Science/Research
Classifier: License :: OSI Approved :: GNU General Public License v3 (GPLv3)
Classifier: Programming Language :: Python :: 2
Classifier: Programming Language :: Python :: 2.7
Classifier: Programming Language :: Python :: 3
Classifier: Programming Language :: Python :: 3.4
Classifier: Programming Language :: Python :: 3.5
Classifier: Topic :: Scientific/Engineering :: Artificial Intelligence
Classifier: Topic :: Utilities
